teletracker/__init__.py
teletracker/files.py
teletracker/unified_logger.py
teletracker-0.0.1.dist-info/LICENSE
teletracker-0.0.1.dist-info/METADATA
teletracker-0.0.1.dist-info/WHEEL
teletracker-0.0.1.dist-info/RECORD
