Metadata-Version: 2.3
Name: teletracker
Version: 0.0.1
Summary: A Python logging handler that bridges Python's logging module with Telegram, enabling direct sending of log messages and files to Telegram chats.
License: Apache-2.0
Author: Duccioo
Author-email: meconcelliduccio@hotmail.it
Requires-Python: >=3.12
Classifier: License :: OSI Approved :: Apache Software License
Classifier: Programming Language :: Python :: 3
Classifier: Programming Language :: Python :: 3.12
Classifier: Programming Language :: Python :: 3.13
Requires-Dist: pytelegrambotapi (>=4.27.0,<5.0.0)
Requires-Dist: requests (>=2.32.3,<3.0.0)
